devtools_twitter_card/__init__.py
devtools_twitter_card-1.0.1.dist-info/METADATA
devtools_twitter_card-1.0.1.dist-info/WHEEL
devtools_twitter_card-1.0.1.dist-info/top_level.txt
devtools_twitter_card-1.0.1.dist-info/RECORD
