Metadata-Version: 2.1
Name: devtools_twitter_card
Version: 1.0.1
Summary: Twitter Card generator
Home-page: https://devtools.at/tools/twitter-card-generator
Author: DevTools.at
Author-email: hello@devtools.at
Project-URL: Homepage, https://devtools.at/tools/twitter-card-generator
Project-URL: Repository, https://github.com/devtools-at/twitter-card-generator
Classifier: Development Status :: 4 - Beta
Classifier: Intended Audience :: Developers
Classifier: License :: OSI Approved :: MIT License
Classifier: Programming Language :: Python :: 3
Requires-Python: >=3.8
